README.md
setup.cfg
setup.py
anhSMSwrap/__init__.py
anhSMSwrap/actions.py
anhSMSwrap/activations.py
anhSMSwrap/datatype.py
anhSMSwrap/errors.py
anhSMSwrap/helper.py
anhSMSwrap/models.py
anhSMSwrap/services.py
anhSMSwrap/setup.py
anhSMSwrap/sms.py
anhSMSwrap/types.py
anhSMSwrap.egg-info/PKG-INFO
anhSMSwrap.egg-info/SOURCES.txt
anhSMSwrap.egg-info/dependency_links.txt
anhSMSwrap.egg-info/top_level.txt